{"_type":"export","__export_format":4,"__export_date":"2023-11-28T19:05:58.499Z","__export_source":"insomnia.desktop.app:v2023.5.8","resources":[{"_id":"req_337399b9ecf346a998727d3678fd4c71","parentId":"wrk_48dc57c2a0aa4049b40c9a9a4b401e0f","modified":1701197979344,"created":1701196005601,"url":"http://localhost:3000/notificacao/inscricao-liberada","name":"Avanço na fila de espera","description":"","method":"GET","body":{"mimeType":"application/json","text":"{\n  \"destinatarioEmail\":\"jorge_william_cardoso@yahoo.com.br\",\n  \"destinatarioNome\" :\"Jorge William\",\n  \"cursosSelecionados\": [\"Ballet\", \"Natação\"],\n\t\"escola\":\"liceu\"\n}"},"parameters":[],"headers":[{"name":"Content-Type","value":"application/json"},{"name":"User-Agent","value":"insomnia/2023.5.8"}],"authentication":{},"metaSortKey":-1701196005601,"isPrivate":false,"settingStoreCookies":true,"settingSendCookies":true,"settingDisableRenderRequestBody":false,"settingEncodeUrl":true,"settingRebuildPath":true,"settingFollowRedirects":"global","_type":"request"},{"_id":"wrk_48dc57c2a0aa4049b40c9a9a4b401e0f","parentId":null,"modified":1701195970203,"created":1701183834637,"name":"Liceu Franco ","description":"","scope":"collection","_type":"workspace"},{"_id":"req_df42576d7be849d79f8492197c5880fd","parentId":"wrk_48dc57c2a0aa4049b40c9a9a4b401e0f","modified":1701196465077,"created":1701195955419,"url":"http://localhost:3000/notificacao/tempo-expirado","name":"Tempo de inscrição expirado","description":"","method":"GET","body":{"mimeType":"application/json","text":"{\n  \"destinatarioEmail\":\"jorge_william_cardoso@yahoo.com.br\",\n  \"destinatarioNome\" :\"Jorge William\",\n  \"cursosSelecionados\": [\"Ballet\", \"Natação\"],\n\t\"escola\":\"liceu\"\n}"},"parameters":[],"headers":[{"name":"Content-Type","value":"application/json"},{"name":"User-Agent","value":"insomnia/2023.5.8"}],"authentication":{},"metaSortKey":-1701195955419,"isPrivate":false,"settingStoreCookies":true,"settingSendCookies":true,"settingDisableRenderRequestBody":false,"settingEncodeUrl":true,"settingRebuildPath":true,"settingFollowRedirects":"global","_type":"request"},{"_id":"req_003c0ff8ab4f417ea4abc1fcb921316a","parentId":"wrk_48dc57c2a0aa4049b40c9a9a4b401e0f","modified":1701196459514,"created":1701183843416,"url":"http://localhost:3000/notificacao/confirmacao-inscricao","name":"Confirmacao de inscrição","description":"","method":"GET","body":{"mimeType":"application/json","text":"{\n\t\"destinatarioEmail\":\"jorge_william_cardoso@yahoo.com.br\",\n  \"destinatarioNome\" :\"Jorge William\",\n  \"cursosSelecionados\":[\"Ballet\", \"Natação\"],\n\t\"escola\":\"liceu\"\n}"},"parameters":[],"headers":[{"name":"Content-Type","value":"application/json"},{"name":"User-Agent","value":"insomnia/2023.5.8"}],"authentication":{},"metaSortKey":-1701183843416,"isPrivate":false,"settingStoreCookies":true,"settingSendCookies":true,"settingDisableRenderRequestBody":false,"settingEncodeUrl":true,"settingRebuildPath":true,"settingFollowRedirects":"global","_type":"request"},{"_id":"env_1a36ba00de3842c04cf9bceace73d3b731c2c1a0","parentId":"wrk_48dc57c2a0aa4049b40c9a9a4b401e0f","modified":1701183834650,"created":1701183834650,"name":"Base Environment","data":{},"dataPropertyOrder":null,"color":null,"isPrivate":false,"metaSortKey":1701183834650,"_type":"environment"},{"_id":"jar_1a36ba00de3842c04cf9bceace73d3b731c2c1a0","parentId":"wrk_48dc57c2a0aa4049b40c9a9a4b401e0f","modified":1701183834653,"created":1701183834653,"name":"Default Jar","cookies":[],"_type":"cookie_jar"}]}